{"scores":[{"playerInitials":"KAM","score":94,"recordedAt":1},{"playerInitials":"KAM","score":87,"recordedAt":1},{"playerInitials":"KAM","score":79,"recordedAt":0},{"playerInitials":"KAM","score":74,"recordedAt":0},{"playerInitials":"KAM","score":66,"recordedAt":1644},{"playerInitials":"KAM","score":64,"recordedAt":1644},{"playerInitials":"KAM","score":51,"recordedAt":1},{"playerInitials":"KAM","score":25,"recordedAt":1644219154},{"playerInitials":"KAM","score":23,"recordedAt":1644219183250},{"playerInitials":"KAM","score":16,"recordedAt":1},{"playerInitials":"KAM","score":12,"recordedAt":1644}]}